pydeepspeech/__init__.py
pydeepspeech/audio_transcript_cmd.py
pydeepspeech/install_models.py
pydeepspeech/interactive_install_modules.py
pydeepspeech/paths.py
pydeepspeech/run.py
pydeepspeech/transcribe.py
pydeepspeech/util.py
pydeepspeech/wavSplit.py
pydeepspeech/wavTranscriber.py
pydeepspeech/wav_split.py
pydeepspeech/wav_transcriber.py
pydeepspeech-1.1.7.dist-info/LICENSE
pydeepspeech-1.1.7.dist-info/METADATA
pydeepspeech-1.1.7.dist-info/WHEEL
pydeepspeech-1.1.7.dist-info/entry_points.txt
pydeepspeech-1.1.7.dist-info/top_level.txt
pydeepspeech-1.1.7.dist-info/RECORD
