Metadata-Version: 2.1
Name: pydeepspeech
Version: 1.1.7
Summary: Mozilla's DeepSpeech transcriber in a pip installable package.
Home-page: https://github.com/zackees/pydeepspeech
Author: Zach Vorhies
Author-email: dont@email.me
License: MIT
Platform: UNKNOWN
Classifier: License :: OSI Approved :: MIT License
Classifier: Programming Language :: Python :: 3.6
Classifier: Programming Language :: Python :: 3.8
Requires-Python: >=3.6.0
License-File: LICENSE
Requires-Dist: deepspeech (==0.9.3)
Requires-Dist: webrtcvad
Requires-Dist: pathlib
Requires-Dist: capturing-process
Requires-Dist: requests
Requires-Dist: black
Provides-Extra: test
Requires-Dist: pytest ; extra == 'test'
